pyIpeaData/__init__.py
pyIpeaData-0.0.1.dist-info/LICENSE
pyIpeaData-0.0.1.dist-info/METADATA
pyIpeaData-0.0.1.dist-info/WHEEL
pyIpeaData-0.0.1.dist-info/top_level.txt
pyIpeaData-0.0.1.dist-info/RECORD
