Metadata-Version: 2.1
Name: pyIpeaData
Version: 0.0.1
Summary: Pacote para obter dados do Ipea Data
Home-page: https://github.com/danielsioli/IpeaData
Author: Gustavo Coelho, Daniel Oliveira
Author-email: danielsioli@gmail.com
License: Creative Commons Attribution-Noncommercial-Share Alike license
Keywords: ipea
Platform: UNKNOWN
Classifier: Development Status :: 4 - Beta
Classifier: Intended Audience :: Developers
Classifier: Topic :: Internet :: WWW/HTTP
Classifier: Programming Language :: Python :: 3
Classifier: Programming Language :: Python :: 3.3
Classifier: Programming Language :: Python :: 3.4
Classifier: Programming Language :: Python :: 3.5
Requires-Dist: requests
Requires-Dist: pandas
